{
  "timestamp": 1776740777.962522,
  "git_head": "eb8e5cad16363fc50188ae33e4b4a68e994ed3ae",
  "tasks": [
    {
      "priority": "P1",
      "category": "test-depth",
      "title": "Expand tests for ZoneServer (34 tests for 1468 lines)",
      "description": "Source file has 1468 lines but only 34 test cases \u2014 need 36+",
      "files": [
        "src/server/src/zones/ZoneServer.cpp",
        "src/server/tests/TestZoneServer.cpp"
      ],
      "estimated_hours": 2.0
    },
    {
      "priority": "P2",
      "category": "test",
      "title": "Add tests for GuildSystem",
      "description": "No test file found for src/server/src/combat/GuildSystem.cpp",
      "files": [
        "src/server/src/combat/GuildSystem.cpp"
      ],
      "estimated_hours": 1.0
    },
    {
      "priority": "P2",
      "category": "test",
      "title": "Add tests for PartySystem",
      "description": "No test file found for src/server/src/combat/PartySystem.cpp",
      "files": [
        "src/server/src/combat/PartySystem.cpp"
      ],
      "estimated_hours": 1.0
    },
    {
      "priority": "P2",
      "category": "docs",
      "title": "Update 3 stale documentation files",
      "description": "Documentation references old project state \u2014 needs alignment with current implementation",
      "files": [
        "DOCUMENTATION_SYNC_REPORT.md",
        "DarkAges_Comprehensive_Review.md",
        "PROJECT_STATUS.md"
      ],
      "estimated_hours": 2.0
    },
    {
      "priority": "P3",
      "category": "refactor",
      "title": "Refactor NPCAISystem.cpp (730 lines)",
      "description": "File is 730 lines with cleanup potential",
      "files": [
        "src/server/src/combat/NPCAISystem.cpp"
      ],
      "estimated_hours": 3.0
    },
    {
      "priority": "P3",
      "category": "refactor",
      "title": "Reduce includes in ZoneServer.hpp (45 includes)",
      "description": "Header has 45 #include directives \u2014 consider forward declarations",
      "files": [
        "src/server/include/zones/ZoneServer.hpp"
      ],
      "estimated_hours": 1.0
    }
  ]
}